pypolca/__init__.py
pypolca/utils/CITATION
pypolca/utils/VERSION
pypolca/utils/external_tools.py
pypolca/utils/fix_consensus_from_vcf.py
pypolca/utils/mapping.py
pypolca/utils/processing.py
pypolca/utils/report.py
pypolca/utils/util.py
pypolca/utils/validation.py
pypolca/utils/variants.py
pypolca-0.4.0.dist-info/AUTHORS.md
pypolca-0.4.0.dist-info/LICENSE
pypolca-0.4.0.dist-info/METADATA
pypolca-0.4.0.dist-info/WHEEL
pypolca-0.4.0.dist-info/entry_points.txt
pypolca-0.4.0.dist-info/RECORD
