Metadata-Version: 2.3
Name: pypolca
Version: 0.4.0
Summary: Standalone Python implementation of the POLCA polisher from MaSuRCA
License: MIT
Keywords: microbial,bioinformatics
Author: George Bouras
Author-email: george.bouras@adelaide.edu.au
Requires-Python: >=3.7,<4.0
Classifier: License :: OSI Approved :: MIT License
Classifier: Programming Language :: Python :: 3
Classifier: Programming Language :: Python :: 3.7
Classifier: Programming Language :: Python :: 3.8
Classifier: Programming Language :: Python :: 3.9
Classifier: Programming Language :: Python :: 3.10
Classifier: Programming Language :: Python :: 3.11
Classifier: Programming Language :: Python :: 3.12
Classifier: Programming Language :: Python :: 3.13
Requires-Dist: biopython (>=1.76)
Requires-Dist: click (>=8.0.0)
Requires-Dist: loguru (>=0.5.3)
Requires-Dist: pyyaml (>=6.0)
Project-URL: Homepage, https://github.com/gbouras13/pypolca
Project-URL: Repository, https://github.com/gbouras13/pypolca
